libname/__init__.py
libname/hello.py
Tes0204-0.0.1.dist-info/METADATA
Tes0204-0.0.1.dist-info/WHEEL
Tes0204-0.0.1.dist-info/top_level.txt
Tes0204-0.0.1.dist-info/RECORD
