Metadata-Version: 2.1
Name: Tes0204
Version: 0.0.1
Summary: Tes
Home-page: UNKNOWN
Author: Vijayakumar
Author-email: <x21188955@student.ncirl.ie>
License: UNKNOWN
Keywords: python,video,stream,video stream,camera stream,sockets
Platform: UNKNOWN
Classifier: Development Status :: 1 - Planning
Classifier: Intended Audience :: Developers
Classifier: Programming Language :: Python :: 3
Classifier: Operating System :: Unix
Classifier: Operating System :: MacOS :: MacOS X
Classifier: Operating System :: Microsoft :: Windows
